{"data":{"doczDb":{"id":"ace00e2b-9c46-5e24-a19a-5ed242ca9c64","db":"{\"config\":{\"title\":\"组件库\",\"description\":\"My awesome app using docz\",\"menu\":[],\"version\":\"2.0.0-rc.41\",\"repository\":null,\"native\":false,\"themeConfig\":{},\"separator\":\"-\",\"typescript\":true,\"base\":\"/docz/\"},\"entries\":[{\"key\":\"README.md\",\"value\":{\"id\":\"04c6e90faac2675aa89e2176d2eec7d8\",\"filepath\":\"README.md\",\"fullpath\":\"/home/travis/build/Messiahhh/docz/README.md\",\"link\":\"\",\"hidden\":false,\"slug\":\"readme\",\"route\":\"/readme\",\"name\":\"Readme\",\"menu\":\"\",\"headings\":[{\"slug\":\"typescript-docz-example\",\"depth\":1,\"value\":\"Typescript Docz example\"},{\"slug\":\"using-create-docz-app\",\"depth\":2,\"value\":\"Using  create-docz-app\"},{\"slug\":\"download-manually\",\"depth\":2,\"value\":\"Download manually\"},{\"slug\":\"setup\",\"depth\":2,\"value\":\"Setup\"},{\"slug\":\"run\",\"depth\":2,\"value\":\"Run\"}]}},{\"key\":\"src/index.mdx\",\"value\":{\"name\":\"Getting Started\",\"route\":\"/\",\"id\":\"6576455a124f9aaefd860597f03a8fe4\",\"filepath\":\"src/index.mdx\",\"fullpath\":\"/home/travis/build/Messiahhh/docz/src/index.mdx\",\"link\":\"\",\"hidden\":false,\"slug\":\"src-index\",\"menu\":\"\",\"headings\":[{\"slug\":\"getting-started\",\"depth\":1,\"value\":\"Getting Started\"},{\"slug\":\"consistency\",\"depth\":2,\"value\":\"Consistency\"}]}},{\"key\":\"src/components/Button.mdx\",\"value\":{\"name\":\"Button\",\"menu\":\"Components\",\"id\":\"94c04b4e4bd29ffbdeec8755c1a4c04f\",\"filepath\":\"src/components/Button.mdx\",\"fullpath\":\"/home/travis/build/Messiahhh/docz/src/components/Button.mdx\",\"link\":\"\",\"hidden\":false,\"slug\":\"src-components-button\",\"route\":\"/src-components-button\",\"headings\":[{\"slug\":\"按钮\",\"depth\":1,\"value\":\"按钮\"},{\"slug\":\"button属性\",\"depth\":2,\"value\":\"Button属性\"},{\"slug\":\"基本用法\",\"depth\":2,\"value\":\"基本用法\"}]}},{\"key\":\"src/components/Tabs.mdx\",\"value\":{\"name\":\"Tabs\",\"menu\":\"Components\",\"id\":\"91f56848ebda28a2ec7bcabc82201316\",\"filepath\":\"src/components/Tabs.mdx\",\"fullpath\":\"/home/travis/build/Messiahhh/docz/src/components/Tabs.mdx\",\"link\":\"\",\"hidden\":false,\"slug\":\"src-components-tabs\",\"route\":\"/src-components-tabs\",\"headings\":[{\"slug\":\"标签页\",\"depth\":1,\"value\":\"标签页\"},{\"slug\":\"tab属性\",\"depth\":2,\"value\":\"Tab属性\"},{\"slug\":\"tabpane属性\",\"depth\":2,\"value\":\"TabPane属性\"},{\"slug\":\"基本用法\",\"depth\":2,\"value\":\"基本用法\"},{\"slug\":\"位置\",\"depth\":2,\"value\":\"位置\"},{\"slug\":\"卡片样式\",\"depth\":2,\"value\":\"卡片样式\"}]}},{\"key\":\"src/components/test.mdx\",\"value\":{\"name\":\"Test\",\"menu\":\"Components\",\"id\":\"6fb2542b846079b72585389a769b9c57\",\"filepath\":\"src/components/test.mdx\",\"fullpath\":\"/home/travis/build/Messiahhh/docz/src/components/test.mdx\",\"link\":\"\",\"hidden\":false,\"slug\":\"src-components-test\",\"route\":\"/src-components-test\",\"headings\":[{\"slug\":\"测试板块\",\"depth\":1,\"value\":\"测试板块\"},{\"slug\":\"基本用法\",\"depth\":2,\"value\":\"基本用法\"}]}}],\"props\":[{\"key\":\"src/components/Button.tsx\",\"value\":[{\"description\":\"\",\"displayName\":\"Button\",\"methods\":[],\"props\":{\"type\":{\"defaultValue\":null,\"description\":\"\",\"name\":\"type\",\"parent\":{\"fileName\":\"src/components/Button.tsx\",\"name\":\"ButtonPropsType\"},\"required\":false,\"type\":{\"name\":\"string | undefined\"}}}}]},{\"key\":\"src/components/Tabs.tsx\",\"value\":[{\"description\":\"\",\"displayName\":\"Tabs\",\"methods\":[],\"props\":{\"defaultActiveIndex\":{\"defaultValue\":null,\"description\":\"\",\"name\":\"defaultActiveIndex\",\"parent\":{\"fileName\":\"src/components/Tabs.tsx\",\"name\":\"TabsProps\"},\"required\":false,\"type\":{\"name\":\"string | undefined\"}},\"type\":{\"defaultValue\":null,\"description\":\"\",\"name\":\"type\",\"parent\":{\"fileName\":\"src/components/Tabs.tsx\",\"name\":\"TabsProps\"},\"required\":false,\"type\":{\"name\":\"\\\"line\\\" | \\\"card\\\" | undefined\"}},\"size\":{\"defaultValue\":null,\"description\":\"\",\"name\":\"size\",\"parent\":{\"fileName\":\"src/components/Tabs.tsx\",\"name\":\"TabsProps\"},\"required\":false,\"type\":{\"name\":\"\\\"small\\\" | \\\"default\\\" | \\\"large\\\" | undefined\"}},\"tabPosition\":{\"defaultValue\":null,\"description\":\"\",\"name\":\"tabPosition\",\"parent\":{\"fileName\":\"src/components/Tabs.tsx\",\"name\":\"TabsProps\"},\"required\":false,\"type\":{\"name\":\"\\\"left\\\" | \\\"right\\\" | \\\"top\\\" | \\\"bottom\\\" | undefined\"}},\"onChange\":{\"defaultValue\":null,\"description\":\"\",\"name\":\"onChange\",\"parent\":{\"fileName\":\"src/components/Tabs.tsx\",\"name\":\"TabsProps\"},\"required\":false,\"type\":{\"name\":\"((before: string, after: string) => void) | undefined\"}}}},{\"description\":\"\",\"displayName\":\"TabPane\",\"methods\":[],\"props\":{\"label\":{\"defaultValue\":null,\"description\":\"\",\"name\":\"label\",\"parent\":{\"fileName\":\"src/components/Tabs.tsx\",\"name\":\"TabPaneProps\"},\"required\":false,\"type\":{\"name\":\"string | undefined\"}},\"index\":{\"defaultValue\":null,\"description\":\"\",\"name\":\"index\",\"parent\":{\"fileName\":\"src/components/Tabs.tsx\",\"name\":\"TabPaneProps\"},\"required\":false,\"type\":{\"name\":\"string | undefined\"}},\"disabled\":{\"defaultValue\":null,\"description\":\"\",\"name\":\"disabled\",\"parent\":{\"fileName\":\"src/components/Tabs.tsx\",\"name\":\"TabPaneProps\"},\"required\":false,\"type\":{\"name\":\"boolean | undefined\"}}}}]},{\"key\":\"src/components/Test.tsx\",\"value\":[{\"description\":\"\",\"displayName\":\"Test\",\"methods\":[],\"props\":{}}]}]}"}}}